{
  "summary_excel": {
    "ytd_summary": [
      {
        "market": "Denmark",
        "media": "TV",
        "total_net_net_spend": 0,
        "total_addressable_net_net_spend": 0,
        "total_net_net_measured": 0,
        "measured_spend_percent": 0.0,
        "savings_value": 0,
        "savings_percent": 0.0,
        "inflation_percent": 4.0,
        "inflation_mitigation_percent": 2.0,
        "inflation_after_mitigation_percent": 2.0
      },
      {
        "market": "Denmark",
        "media": "Print",
        "total_net_net_spend": 0,
        "total_addressable_net_net_spend": 0,
        "total_net_net_measured": 0,
        "measured_spend_percent": 0.0,
        "savings_value": 0,
        "savings_percent": 0.0,
        "inflation_percent": 0.0,
        "inflation_mitigation_percent": 0.0,
        "inflation_after_mitigation_percent": 0.0
      },
      {
        "market": "Denmark",
        "media": "OOH",
        "total_net_net_spend": 0,
        "total_addressable_net_net_spend": 0,
        "total_net_net_measured": 0,
        "measured_spend_percent": 0.0,
        "savings_value": 0,
        "savings_percent": 0.0,
        "inflation_percent": null,
        "inflation_mitigation_percent": null,
        "inflation_after_mitigation_percent": 0.0
      },
      {
        "market": "Denmark",
        "media": "Online",
        "total_net_net_spend": 0,
        "total_addressable_net_net_spend": 0,
        "total_net_net_measured": 0,
        "measured_spend_percent": 0.0,
        "savings_value": 0,
        "savings_percent": 0.0,
        "inflation_percent": 3.0,
        "inflation_mitigation_percent": 1.5,
        "inflation_after_mitigation_percent": 1.5
      },
      {
        "market": "Denmark",
        "media": "Radio",
        "total_net_net_spend": 0,
        "total_addressable_net_net_spend": 0,
        "total_net_net_measured": 0,
        "measured_spend_percent": 0.0,
        "savings_value": 0,
        "savings_percent": 0.0,
        "inflation_percent": 0.0,
        "inflation_mitigation_percent": 0.0,
        "inflation_after_mitigation_percent": false
      },
      {
        "market": "Denmark",
        "media": "Cinema",
        "total_net_net_spend": 0,
        "total_addressable_net_net_spend": 0,
        "total_net_net_measured": 0,
        "measured_spend_percent": 0.0,
        "savings_value": 0,
        "savings_percent": 0.0,
        "inflation_percent": 0.0,
        "inflation_mitigation_percent": 0.0,
        "inflation_after_mitigation_percent": false
      },
      {
        "market": "Denmark",
        "media": "Other",
        "total_net_net_spend": 0,
        "total_addressable_net_net_spend": 0,
        "total_net_net_measured": 0,
        "measured_spend_percent": 0.0,
        "savings_value": 0,
        "savings_percent": 0.0,
        "inflation_percent": 0.0,
        "inflation_mitigation_percent": 0.0,
        "inflation_after_mitigation_percent": 0.0
      },
      {
        "market": "Denmark",
        "media": "TOTAL",
        "total_net_net_spend": 0,
        "total_addressable_net_net_spend": 0,
        "total_net_net_measured": 0,
        "measured_spend_percent": 0.0,
        "savings_value": 0,
        "savings_percent": 0.0,
        "inflation_percent": 0.0,
        "inflation_mitigation_percent": 0.0,
        "inflation_after_mitigation_percent": 0.0
      },
      {
        "market": "Netherlands",
        "media": "TV",
        "total_net_net_spend": 1236606,
        "total_addressable_net_net_spend": 1236606,
        "total_net_net_measured": 0,
        "measured_spend_percent": 0.0,
        "savings_value": 0,
        "savings_percent": 0.0,
        "inflation_percent": 15.0,
        "inflation_mitigation_percent": 7.5,
        "inflation_after_mitigation_percent": 7.5
      },
      {
        "market": "Netherlands",
        "media": "Print",
        "total_net_net_spend": 0,
        "total_addressable_net_net_spend": 0,
        "total_net_net_measured": 0,
        "measured_spend_percent": 0.0,
        "savings_value": 0,
        "savings_percent": 0.0,
        "inflation_percent": 0.0,
        "inflation_mitigation_percent": 2.0,
        "inflation_after_mitigation_percent": 0.0
      },
      {
        "market": "Netherlands",
        "media": "OOH",
        "total_net_net_spend": 1268043,
        "total_addressable_net_net_spend": 1268043,
        "total_net_net_measured": 0,
        "measured_spend_percent": 0.0,
        "savings_value": 0,
        "savings_percent": 0.0,
        "inflation_percent": null,
        "inflation_mitigation_percent": null,
        "inflation_after_mitigation_percent": 0.0
      },
      {
        "market": "Netherlands",
        "media": "Online",
        "total_net_net_spend": 578942,
        "total_addressable_net_net_spend": 578942,
        "total_net_net_measured": 0,
        "measured_spend_percent": 0.0,
        "savings_value": 0,
        "savings_percent": 0.0,
        "inflation_percent": 8.0,
        "inflation_mitigation_percent": 2.6,
        "inflation_after_mitigation_percent": 5.4
      },
      {
        "market": "Netherlands",
        "media": "Radio",
        "total_net_net_spend": 6477,
        "total_addressable_net_net_spend": 6477,
        "total_net_net_measured": 6477,
        "measured_spend_percent": 100.0,
        "savings_value": 1756,
        "savings_percent": 21.3,
        "inflation_percent": 5.0,
        "inflation_mitigation_percent": 3.0,
        "inflation_after_mitigation_percent": 2.0
      },
      {
        "market": "Netherlands",
        "media": "Cinema",
        "total_net_net_spend": 0,
        "total_addressable_net_net_spend": 0,
        "total_net_net_measured": 0,
        "measured_spend_percent": 0.0,
        "savings_value": 0,
        "savings_percent": 0.0,
        "inflation_percent": 2.0,
        "inflation_mitigation_percent": 2.0,
        "inflation_after_mitigation_percent": 0.0
      },
      {
        "market": "Netherlands",
        "media": "Other",
        "total_net_net_spend": 0,
        "total_addressable_net_net_spend": 0,
        "total_net_net_measured": 0,
        "measured_spend_percent": 0.0,
        "savings_value": 0,
        "savings_percent": 0.0,
        "inflation_percent": 0.0,
        "inflation_mitigation_percent": 0.0,
        "inflation_after_mitigation_percent": 0.0
      },
      {
        "market": "Netherlands",
        "media": "TOTAL",
        "total_net_net_spend": 3090068,
        "total_addressable_net_net_spend": 3090068,
        "total_net_net_measured": 6477,
        "measured_spend_percent": 0.2,
        "savings_value": 1756.1,
        "savings_percent": 21.3,
        "inflation_percent": 0.0,
        "inflation_mitigation_percent": 0.0,
        "inflation_after_mitigation_percent": 0.0
      },
      {
        "market": "New Zealand",
        "media": "TV",
        "total_net_net_spend": 0,
        "total_addressable_net_net_spend": 0,
        "total_net_net_measured": 0,
        "measured_spend_percent": 0.0,
        "savings_value": 0,
        "savings_percent": 0.0,
        "inflation_percent": 5.2,
        "inflation_mitigation_percent": 1.5,
        "inflation_after_mitigation_percent": 3.7
      },
      {
        "market": "New Zealand",
        "media": "Print",
        "total_net_net_spend": 0,
        "total_addressable_net_net_spend": 0,
        "total_net_net_measured": 0,
        "measured_spend_percent": 0.0,
        "savings_value": 0,
        "savings_percent": 0.0,
        "inflation_percent": 0.0,
        "inflation_mitigation_percent": 0.3,
        "inflation_after_mitigation_percent": 1.0
      },
      {
        "market": "New Zealand",
        "media": "OOH",
        "total_net_net_spend": 68164,
        "total_addressable_net_net_spend": 68164,
        "total_net_net_measured": 0,
        "measured_spend_percent": 0.0,
        "savings_value": 0,
        "savings_percent": 0.0,
        "inflation_percent": null,
        "inflation_mitigation_percent": null,
        "inflation_after_mitigation_percent": 0.0
      },
      {
        "market": "New Zealand",
        "media": "Online",
        "total_net_net_spend": 228665,
        "total_addressable_net_net_spend": 228665,
        "total_net_net_measured": 0,
        "measured_spend_percent": 0.0,
        "savings_value": 0,
        "savings_percent": 0.0,
        "inflation_percent": 4.1,
        "inflation_mitigation_percent": 1.2,
        "inflation_after_mitigation_percent": 2.9
      },
      {
        "market": "New Zealand",
        "media": "Radio",
        "total_net_net_spend": 0,
        "total_addressable_net_net_spend": 0,
        "total_net_net_measured": 0,
        "measured_spend_percent": 0.0,
        "savings_value": 0,
        "savings_percent": 0.0,
        "inflation_percent": 2.4,
        "inflation_mitigation_percent": 0.6,
        "inflation_after_mitigation_percent": 1.8
      },
      {
        "market": "New Zealand",
        "media": "Cinema",
        "total_net_net_spend": 0,
        "total_addressable_net_net_spend": 0,
        "total_net_net_measured": 0,
        "measured_spend_percent": 0.0,
        "savings_value": 0,
        "savings_percent": 0.0,
        "inflation_percent": 2.6,
        "inflation_mitigation_percent": 0.7,
        "inflation_after_mitigation_percent": 1.9
      },
      {
        "market": "New Zealand",
        "media": "Other",
        "total_net_net_spend": 0,
        "total_addressable_net_net_spend": 0,
        "total_net_net_measured": 0,
        "measured_spend_percent": 0.0,
        "savings_value": 0,
        "savings_percent": 0.0,
        "inflation_percent": 0.0,
        "inflation_mitigation_percent": 0.0,
        "inflation_after_mitigation_percent": 0.0
      },
      {
        "market": "New Zealand",
        "media": "TOTAL",
        "total_net_net_spend": 296830,
        "total_addressable_net_net_spend": 296830,
        "total_net_net_measured": 0,
        "measured_spend_percent": 0.0,
        "savings_value": 0,
        "savings_percent": 0.0,
        "inflation_percent": 0.0,
        "inflation_mitigation_percent": 0.0,
        "inflation_after_mitigation_percent": 0.0
      },
      {
        "market": "Nigeria",
        "media": "TV",
        "total_net_net_spend": null,
        "total_addressable_net_net_spend": null,
        "total_net_net_measured": null,
        "measured_spend_percent": 0.0,
        "savings_value": null,
        "savings_percent": 0.0,
        "inflation_percent": 0.0,
        "inflation_mitigation_percent": 0.0,
        "inflation_after_mitigation_percent": false
      },
      {
        "market": "Nigeria",
        "media": "PRINT",
        "total_net_net_spend": null,
        "total_addressable_net_net_spend": null,
        "total_net_net_measured": null,
        "measured_spend_percent": 0.0,
        "savings_value": null,
        "savings_percent": 0.0,
        "inflation_percent": 0.0,
        "inflation_mitigation_percent": 0.0,
        "inflation_after_mitigation_percent": 0.0
      },
      {
        "market": "Nigeria",
        "media": "OUTDOOR",
        "total_net_net_spend": null,
        "total_addressable_net_net_spend": null,
        "total_net_net_measured": null,
        "measured_spend_percent": 0.0,
        "savings_value": null,
        "savings_percent": 0.0,
        "inflation_percent": 0.0,
        "inflation_mitigation_percent": 0.0,
        "inflation_after_mitigation_percent": false
      },
      {
        "market": "Nigeria",
        "media": "ONLINE",
        "total_net_net_spend": null,
        "total_addressable_net_net_spend": null,
        "total_net_net_measured": null,
        "measured_spend_percent": 0.0,
        "savings_value": null,
        "savings_percent": 0.0,
        "inflation_percent": 0.0,
        "inflation_mitigation_percent": 0.0,
        "inflation_after_mitigation_percent": false
      },
      {
        "market": "Nigeria",
        "media": "RADIO",
        "total_net_net_spend": null,
        "total_addressable_net_net_spend": null,
        "total_net_net_measured": null,
        "measured_spend_percent": 0.0,
        "savings_value": null,
        "savings_percent": 0.0,
        "inflation_percent": 0.0,
        "inflation_mitigation_percent": 0.0,
        "inflation_after_mitigation_percent": false
      },
      {
        "market": "Nigeria",
        "media": "CINEMA",
        "total_net_net_spend": null,
        "total_addressable_net_net_spend": null,
        "total_net_net_measured": null,
        "measured_spend_percent": 0.0,
        "savings_value": null,
        "savings_percent": 0.0,
        "inflation_percent": 0.0,
        "inflation_mitigation_percent": 0.0,
        "inflation_after_mitigation_percent": false
      },
      {
        "market": "Nigeria",
        "media": "OTHER",
        "total_net_net_spend": null,
        "total_addressable_net_net_spend": null,
        "total_net_net_measured": null,
        "measured_spend_percent": 0.0,
        "savings_value": null,
        "savings_percent": 0.0,
        "inflation_percent": 0.0,
        "inflation_mitigation_percent": 0.0,
        "inflation_after_mitigation_percent": 0.0
      },
      {
        "market": "Nigeria",
        "media": "TOTAL",
        "total_net_net_spend": 0,
        "total_addressable_net_net_spend": 0,
        "total_net_net_measured": 0,
        "measured_spend_percent": 0.0,
        "savings_value": 0,
        "savings_percent": 0.0,
        "inflation_percent": 0.0,
        "inflation_mitigation_percent": 0.0,
        "inflation_after_mitigation_percent": 0.0
      },
      {
        "market": "Poland",
        "media": "TV",
        "total_net_net_spend": 373257,
        "total_addressable_net_net_spend": 373257,
        "total_net_net_measured": 373257,
        "measured_spend_percent": 100.0,
        "savings_value": 168308,
        "savings_percent": 31.08,
        "inflation_percent": 14.8,
        "inflation_mitigation_percent": 14.8,
        "inflation_after_mitigation_percent": 0.0
      },
      {
        "market": "Poland",
        "media": "Print",
        "total_net_net_spend": 0,
        "total_addressable_net_net_spend": 0,
        "total_net_net_measured": 0,
        "measured_spend_percent": 0.0,
        "savings_value": 0,
        "savings_percent": 0.0,
        "inflation_percent": 0.0,
        "inflation_mitigation_percent": 1.4,
        "inflation_after_mitigation_percent": 0.0
      },
      {
        "market": "Poland",
        "media": "OOH",
        "total_net_net_spend": 4295267,
        "total_addressable_net_net_spend": 4295267,
        "total_net_net_measured": 0,
        "measured_spend_percent": 0.0,
        "savings_value": 0,
        "savings_percent": 0.0,
        "inflation_percent": null,
        "inflation_mitigation_percent": null,
        "inflation_after_mitigation_percent": 0.0
      },
      {
        "market": "Poland",
        "media": "Online",
        "total_net_net_spend": 1382155,
        "total_addressable_net_net_spend": 1382155,
        "total_net_net_measured": 0,
        "measured_spend_percent": 0.0,
        "savings_value": 0,
        "savings_percent": 0.0,
        "inflation_percent": 11.0,
        "inflation_mitigation_percent": 11.0,
        "inflation_after_mitigation_percent": 0.0
      },
      {
        "market": "Poland",
        "media": "Radio",
        "total_net_net_spend": 0,
        "total_addressable_net_net_spend": 0,
        "total_net_net_measured": 0,
        "measured_spend_percent": 0.0,
        "savings_value": 0,
        "savings_percent": 0.0,
        "inflation_percent": 7.5,
        "inflation_mitigation_percent": 7.5,
        "inflation_after_mitigation_percent": 0.0
      },
      {
        "market": "Poland",
        "media": "Cinema",
        "total_net_net_spend": 0,
        "total_addressable_net_net_spend": 0,
        "total_net_net_measured": 0,
        "measured_spend_percent": 0.0,
        "savings_value": 0,
        "savings_percent": 0.0,
        "inflation_percent": 4.6,
        "inflation_mitigation_percent": 4.6,
        "inflation_after_mitigation_percent": 0.0
      },
      {
        "market": "Poland",
        "media": "Other",
        "total_net_net_spend": 0,
        "total_addressable_net_net_spend": 0,
        "total_net_net_measured": 0,
        "measured_spend_percent": 0.0,
        "savings_value": 0,
        "savings_percent": 0.0,
        "inflation_percent": 0.0,
        "inflation_mitigation_percent": 0.0,
        "inflation_after_mitigation_percent": 0.0
      },
      {
        "market": "Poland",
        "media": "TOTAL",
        "total_net_net_spend": 6050679,
        "total_addressable_net_net_spend": 6050679,
        "total_net_net_measured": 373257,
        "measured_spend_percent": 6.2,
        "savings_value": 168308,
        "savings_percent": 31.1,
        "inflation_percent": 0.0,
        "inflation_mitigation_percent": 0.0,
        "inflation_after_mitigation_percent": 0.0
      },
      {
        "market": "Spain",
        "media": "TV",
        "total_net_net_spend": 213830,
        "total_addressable_net_net_spend": 213830,
        "total_net_net_measured": 213830,
        "measured_spend_percent": 100.0,
        "savings_value": -10902,
        "savings_percent": -5.37,
        "inflation_percent": 7.6,
        "inflation_mitigation_percent": 7.6,
        "inflation_after_mitigation_percent": 0.0
      },
      {
        "market": "Spain",
        "media": "Print",
        "total_net_net_spend": 5500,
        "total_addressable_net_net_spend": 5500,
        "total_net_net_measured": 0,
        "measured_spend_percent": 0.0,
        "savings_value": 0,
        "savings_percent": 0.0,
        "inflation_percent": 0.0,
        "inflation_mitigation_percent": 0.6,
        "inflation_after_mitigation_percent": 0.0
      },
      {
        "market": "Spain",
        "media": "OOH",
        "total_net_net_spend": 109482,
        "total_addressable_net_net_spend": 109482,
        "total_net_net_measured": 0,
        "measured_spend_percent": 0.0,
        "savings_value": 0,
        "savings_percent": 0.0,
        "inflation_percent": null,
        "inflation_mitigation_percent": null,
        "inflation_after_mitigation_percent": 0.0
      },
      {
        "market": "Spain",
        "media": "Online",
        "total_net_net_spend": 306066,
        "total_addressable_net_net_spend": 306066,
        "total_net_net_measured": 194566,
        "measured_spend_percent": 63.6,
        "savings_value": 1172,
        "savings_percent": 0.6,
        "inflation_percent": 4.0,
        "inflation_mitigation_percent": 5.0,
        "inflation_after_mitigation_percent": 0.0
      },
      {
        "market": "Spain",
        "media": "Radio",
        "total_net_net_spend": 0,
        "total_addressable_net_net_spend": 0,
        "total_net_net_measured": 0,
        "measured_spend_percent": 0.0,
        "savings_value": 0,
        "savings_percent": 0.0,
        "inflation_percent": 3.3,
        "inflation_mitigation_percent": 3.3,
        "inflation_after_mitigation_percent": 0.0
      },
      {
        "market": "Spain",
        "media": "Cinema",
        "total_net_net_spend": 0,
        "total_addressable_net_net_spend": 0,
        "total_net_net_measured": 0,
        "measured_spend_percent": 0.0,
        "savings_value": 0,
        "savings_percent": 0.0,
        "inflation_percent": 2.1,
        "inflation_mitigation_percent": 2.1,
        "inflation_after_mitigation_percent": 0.0
      },
      {
        "market": "Spain",
        "media": "Other",
        "total_net_net_spend": 0,
        "total_addressable_net_net_spend": 0,
        "total_net_net_measured": 0,
        "measured_spend_percent": 0.0,
        "savings_value": 0,
        "savings_percent": 0.0,
        "inflation_percent": 0.0,
        "inflation_mitigation_percent": 0.0,
        "inflation_after_mitigation_percent": 0.0
      },
      {
        "market": "Spain",
        "media": "TOTAL",
        "total_net_net_spend": 634877,
        "total_addressable_net_net_spend": 634877,
        "total_net_net_measured": 408396,
        "measured_spend_percent": 64.3,
        "savings_value": -9730,
        "savings_percent": -2.4,
        "inflation_percent": 0.0,
        "inflation_mitigation_percent": 0.0,
        "inflation_after_mitigation_percent": 0.0
      },
      {
        "market": "Sweden",
        "media": "TV",
        "total_net_net_spend": 0,
        "total_addressable_net_net_spend": 0,
        "total_net_net_measured": 0,
        "measured_spend_percent": 0.0,
        "savings_value": -4415327,
        "savings_percent": 100.0,
        "inflation_percent": 7.4,
        "inflation_mitigation_percent": 2.6,
        "inflation_after_mitigation_percent": 3.5
      },
      {
        "market": "Sweden",
        "media": "Print",
        "total_net_net_spend": 260841,
        "total_addressable_net_net_spend": 260841,
        "total_net_net_measured": 0,
        "measured_spend_percent": 0.0,
        "savings_value": 0,
        "savings_percent": 0.0,
        "inflation_percent": 0.0,
        "inflation_mitigation_percent": 0.4,
        "inflation_after_mitigation_percent": 0.7
      },
      {
        "market": "Sweden",
        "media": "OOH",
        "total_net_net_spend": 13677846,
        "total_addressable_net_net_spend": 13677846,
        "total_net_net_measured": 0,
        "measured_spend_percent": 0.0,
        "savings_value": 0,
        "savings_percent": 0.0,
        "inflation_percent": null,
        "inflation_mitigation_percent": null,
        "inflation_after_mitigation_percent": 6.3
      },
      {
        "market": "Sweden",
        "media": "Online",
        "total_net_net_spend": 0,
        "total_addressable_net_net_spend": 0,
        "total_net_net_measured": 0,
        "measured_spend_percent": 0.0,
        "savings_value": -58866,
        "savings_percent": 100.0,
        "inflation_percent": 4.0,
        "inflation_mitigation_percent": 1.4,
        "inflation_after_mitigation_percent": 0.4
      },
      {
        "market": "Sweden",
        "media": "Radio",
        "total_net_net_spend": 386702,
        "total_addressable_net_net_spend": 386702,
        "total_net_net_measured": 386702,
        "measured_spend_percent": 100.0,
        "savings_value": 52195,
        "savings_percent": 11.9,
        "inflation_percent": 12.0,
        "inflation_mitigation_percent": 4.2,
        "inflation_after_mitigation_percent": 3.7
      },
      {
        "market": "Sweden",
        "media": "Cinema",
        "total_net_net_spend": 0,
        "total_addressable_net_net_spend": 0,
        "total_net_net_measured": 0,
        "measured_spend_percent": 0.0,
        "savings_value": 0,
        "savings_percent": 0.0,
        "inflation_percent": 3.0,
        "inflation_mitigation_percent": 1.1,
        "inflation_after_mitigation_percent": 4.3
      },
      {
        "market": "Sweden",
        "media": "Other",
        "total_net_net_spend": 0,
        "total_addressable_net_net_spend": 0,
        "total_net_net_measured": 0,
        "measured_spend_percent": 0.0,
        "savings_value": 0,
        "savings_percent": 0.0,
        "inflation_percent": 0.0,
        "inflation_mitigation_percent": 0.0,
        "inflation_after_mitigation_percent": 0.0
      },
      {
        "market": "Sweden",
        "media": "TOTAL",
        "total_net_net_spend": 14325389,
        "total_addressable_net_net_spend": 14325389,
        "total_net_net_measured": 386702,
        "measured_spend_percent": 2.7,
        "savings_value": -4421998,
        "savings_percent": 109.6,
        "inflation_percent": 0.0,
        "inflation_mitigation_percent": 0.0,
        "inflation_after_mitigation_percent": 0.0
      },
      {
        "market": "UK",
        "media": "TV",
        "total_net_net_spend": 2617284,
        "total_addressable_net_net_spend": 2617284,
        "total_net_net_measured": 2601702,
        "measured_spend_percent": 99.4,
        "savings_value": -282857,
        "savings_percent": -12.2,
        "inflation_percent": 9.0,
        "inflation_mitigation_percent": 0.0,
        "inflation_after_mitigation_percent": 6.9
      },
      {
        "market": "UK",
        "media": "Print",
        "total_net_net_spend": 0,
        "total_addressable_net_net_spend": 0,
        "total_net_net_measured": 0,
        "measured_spend_percent": 0.0,
        "savings_value": 0,
        "savings_percent": 0.0,
        "inflation_percent": 0.0,
        "inflation_mitigation_percent": 0.0,
        "inflation_after_mitigation_percent": 0.0
      },
      {
        "market": "UK",
        "media": "OOH",
        "total_net_net_spend": 5344838,
        "total_addressable_net_net_spend": 5344838,
        "total_net_net_measured": 5344838,
        "measured_spend_percent": 100.0,
        "savings_value": 0,
        "savings_percent": 0.0,
        "inflation_percent": null,
        "inflation_mitigation_percent": 0.0,
        "inflation_after_mitigation_percent": 0.0
      },
      {
        "market": "UK",
        "media": "Online",
        "total_net_net_spend": 2401724,
        "total_addressable_net_net_spend": 2401724,
        "total_net_net_measured": 1377610,
        "measured_spend_percent": 57.4,
        "savings_value": 29997,
        "savings_percent": 2.1,
        "inflation_percent": 0.0,
        "inflation_mitigation_percent": 0.0,
        "inflation_after_mitigation_percent": false
      },
      {
        "market": "UK",
        "media": "Radio",
        "total_net_net_spend": 0,
        "total_addressable_net_net_spend": 0,
        "total_net_net_measured": 0,
        "measured_spend_percent": 0.0,
        "savings_value": 0,
        "savings_percent": 0.0,
        "inflation_percent": 0.0,
        "inflation_mitigation_percent": 0.0,
        "inflation_after_mitigation_percent": false
      },
      {
        "market": "UK",
        "media": "Cinema",
        "total_net_net_spend": 0,
        "total_addressable_net_net_spend": 0,
        "total_net_net_measured": 0,
        "measured_spend_percent": 0.0,
        "savings_value": 0,
        "savings_percent": 0.0,
        "inflation_percent": 0.0,
        "inflation_mitigation_percent": 0.0,
        "inflation_after_mitigation_percent": false
      },
      {
        "market": "UK",
        "media": "Other",
        "total_net_net_spend": 0,
        "total_addressable_net_net_spend": 0,
        "total_net_net_measured": 0,
        "measured_spend_percent": 0.0,
        "savings_value": 0,
        "savings_percent": 0.0,
        "inflation_percent": 0.0,
        "inflation_mitigation_percent": 0.0,
        "inflation_after_mitigation_percent": 0.0
      },
      {
        "market": "UK",
        "media": "TOTAL",
        "total_net_net_spend": 10363846,
        "total_addressable_net_net_spend": 10363846,
        "total_net_net_measured": 9324150,
        "measured_spend_percent": 90.0,
        "savings_value": -252861,
        "savings_percent": -2.8,
        "inflation_percent": 0.0,
        "inflation_mitigation_percent": 0.0,
        "inflation_after_mitigation_percent": 0.0
      }
    ],
    "fy_fc_summary": [
      {
        "market": "Denmark",
        "media": "TV",
        "total_net_net_spend": 0,
        "total_addressable_net_net_spend": 0,
        "total_net_net_measured": 0,
        "measured_spend_percent": 0.0,
        "savings_value": 0,
        "savings_percent": 0.0,
        "inflation_percent": 4.0,
        "inflation_mitigation_percent": 2.0,
        "inflation_after_mitigation_percent": 2.0
      },
      {
        "market": "Denmark",
        "media": "Print",
        "total_net_net_spend": 0,
        "total_addressable_net_net_spend": 0,
        "total_net_net_measured": 0,
        "measured_spend_percent": 0.0,
        "savings_value": 0,
        "savings_percent": 0.0,
        "inflation_percent": 0.0,
        "inflation_mitigation_percent": 0.0,
        "inflation_after_mitigation_percent": 0.0
      },
      {
        "market": "Denmark",
        "media": "OOH",
        "total_net_net_spend": 0,
        "total_addressable_net_net_spend": 0,
        "total_net_net_measured": 0,
        "measured_spend_percent": 0.0,
        "savings_value": 0,
        "savings_percent": 0.0,
        "inflation_percent": null,
        "inflation_mitigation_percent": null,
        "inflation_after_mitigation_percent": null
      },
      {
        "market": "Denmark",
        "media": "Online",
        "total_net_net_spend": 0,
        "total_addressable_net_net_spend": 0,
        "total_net_net_measured": 0,
        "measured_spend_percent": 0.0,
        "savings_value": 0,
        "savings_percent": 0.0,
        "inflation_percent": 3.0,
        "inflation_mitigation_percent": 1.5,
        "inflation_after_mitigation_percent": 1.5
      },
      {
        "market": "Denmark",
        "media": "Radio",
        "total_net_net_spend": 0,
        "total_addressable_net_net_spend": 0,
        "total_net_net_measured": 0,
        "measured_spend_percent": 0.0,
        "savings_value": 0,
        "savings_percent": 0.0,
        "inflation_percent": 0.0,
        "inflation_mitigation_percent": 0.0,
        "inflation_after_mitigation_percent": false
      },
      {
        "market": "Denmark",
        "media": "Cinema",
        "total_net_net_spend": 0,
        "total_addressable_net_net_spend": 0,
        "total_net_net_measured": 0,
        "measured_spend_percent": 0.0,
        "savings_value": 0,
        "savings_percent": 0.0,
        "inflation_percent": 0.0,
        "inflation_mitigation_percent": 0.0,
        "inflation_after_mitigation_percent": false
      },
      {
        "market": "Denmark",
        "media": "Other",
        "total_net_net_spend": 0,
        "total_addressable_net_net_spend": 0,
        "total_net_net_measured": 0,
        "measured_spend_percent": 0.0,
        "savings_value": 0,
        "savings_percent": 0.0,
        "inflation_percent": null,
        "inflation_mitigation_percent": null,
        "inflation_after_mitigation_percent": null
      },
      {
        "market": "Denmark",
        "media": "TOTAL",
        "total_net_net_spend": 0,
        "total_addressable_net_net_spend": 0,
        "total_net_net_measured": 0,
        "measured_spend_percent": 0.0,
        "savings_value": 0,
        "savings_percent": 0.0,
        "inflation_percent": 0.0,
        "inflation_mitigation_percent": 0.0,
        "inflation_after_mitigation_percent": 0.0
      },
      {
        "market": "Netherlands",
        "media": "TV",
        "total_net_net_spend": 1236606,
        "total_addressable_net_net_spend": 1236606,
        "total_net_net_measured": 0,
        "measured_spend_percent": 0.0,
        "savings_value": 0,
        "savings_percent": 0.0,
        "inflation_percent": 15.0,
        "inflation_mitigation_percent": 7.5,
        "inflation_after_mitigation_percent": 7.5
      },
      {
        "market": "Netherlands",
        "media": "Print",
        "total_net_net_spend": 0,
        "total_addressable_net_net_spend": 0,
        "total_net_net_measured": 0,
        "measured_spend_percent": 0.0,
        "savings_value": 0,
        "savings_percent": 0.0,
        "inflation_percent": 0.0,
        "inflation_mitigation_percent": 2.0,
        "inflation_after_mitigation_percent": 0.0
      },
      {
        "market": "Netherlands",
        "media": "OOH",
        "total_net_net_spend": 1268043,
        "total_addressable_net_net_spend": 1268043,
        "total_net_net_measured": 0,
        "measured_spend_percent": 0.0,
        "savings_value": 0,
        "savings_percent": 0.0,
        "inflation_percent": null,
        "inflation_mitigation_percent": null,
        "inflation_after_mitigation_percent": null
      },
      {
        "market": "Netherlands",
        "media": "Online",
        "total_net_net_spend": 578942,
        "total_addressable_net_net_spend": 578942,
        "total_net_net_measured": 0,
        "measured_spend_percent": 0.0,
        "savings_value": 0,
        "savings_percent": 0.0,
        "inflation_percent": 8.0,
        "inflation_mitigation_percent": 2.6,
        "inflation_after_mitigation_percent": 5.4
      },
      {
        "market": "Netherlands",
        "media": "Radio",
        "total_net_net_spend": 6477,
        "total_addressable_net_net_spend": 6477,
        "total_net_net_measured": 6477,
        "measured_spend_percent": 100.0,
        "savings_value": 1756,
        "savings_percent": 21.3,
        "inflation_percent": 5.0,
        "inflation_mitigation_percent": 3.0,
        "inflation_after_mitigation_percent": 2.0
      },
      {
        "market": "Netherlands",
        "media": "Cinema",
        "total_net_net_spend": 0,
        "total_addressable_net_net_spend": 0,
        "total_net_net_measured": 0,
        "measured_spend_percent": 0.0,
        "savings_value": 0,
        "savings_percent": 0.0,
        "inflation_percent": 2.0,
        "inflation_mitigation_percent": 2.0,
        "inflation_after_mitigation_percent": 0.0
      },
      {
        "market": "Netherlands",
        "media": "Other",
        "total_net_net_spend": 0,
        "total_addressable_net_net_spend": 0,
        "total_net_net_measured": 0,
        "measured_spend_percent": 0.0,
        "savings_value": 0,
        "savings_percent": 0.0,
        "inflation_percent": 0.0,
        "inflation_mitigation_percent": 0.0,
        "inflation_after_mitigation_percent": 0.0
      },
      {
        "market": "Netherlands",
        "media": "TOTAL",
        "total_net_net_spend": 3090068,
        "total_addressable_net_net_spend": 3090068,
        "total_net_net_measured": 6477,
        "measured_spend_percent": 0.2,
        "savings_value": 1756,
        "savings_percent": 21.3,
        "inflation_percent": 0.0,
        "inflation_mitigation_percent": 0.0,
        "inflation_after_mitigation_percent": 0.0
      },
      {
        "market": "New Zealand",
        "media": "TV",
        "total_net_net_spend": 0,
        "total_addressable_net_net_spend": 0,
        "total_net_net_measured": 0,
        "measured_spend_percent": 0.0,
        "savings_value": 0,
        "savings_percent": 0.0,
        "inflation_percent": 5.2,
        "inflation_mitigation_percent": 1.5,
        "inflation_after_mitigation_percent": 3.7
      },
      {
        "market": "New Zealand",
        "media": "Print",
        "total_net_net_spend": 0,
        "total_addressable_net_net_spend": 0,
        "total_net_net_measured": 0,
        "measured_spend_percent": 0.0,
        "savings_value": 0,
        "savings_percent": 0.0,
        "inflation_percent": 0.0,
        "inflation_mitigation_percent": 0.3,
        "inflation_after_mitigation_percent": 1.0
      },
      {
        "market": "New Zealand",
        "media": "OOH",
        "total_net_net_spend": 68164,
        "total_addressable_net_net_spend": 68164,
        "total_net_net_measured": 0,
        "measured_spend_percent": 0.0,
        "savings_value": 0,
        "savings_percent": 0.0,
        "inflation_percent": null,
        "inflation_mitigation_percent": null,
        "inflation_after_mitigation_percent": null
      },
      {
        "market": "New Zealand",
        "media": "Online",
        "total_net_net_spend": 228665,
        "total_addressable_net_net_spend": 228665,
        "total_net_net_measured": 0,
        "measured_spend_percent": 0.0,
        "savings_value": 0,
        "savings_percent": 0.0,
        "inflation_percent": 4.1,
        "inflation_mitigation_percent": 1.2,
        "inflation_after_mitigation_percent": 2.9
      },
      {
        "market": "New Zealand",
        "media": "Radio",
        "total_net_net_spend": 0,
        "total_addressable_net_net_spend": 0,
        "total_net_net_measured": 0,
        "measured_spend_percent": 0.0,
        "savings_value": 0,
        "savings_percent": 0.0,
        "inflation_percent": 2.4,
        "inflation_mitigation_percent": 0.6,
        "inflation_after_mitigation_percent": 1.8
      },
      {
        "market": "New Zealand",
        "media": "Cinema",
        "total_net_net_spend": 0,
        "total_addressable_net_net_spend": 0,
        "total_net_net_measured": 0,
        "measured_spend_percent": 0.0,
        "savings_value": 0,
        "savings_percent": 0.0,
        "inflation_percent": 2.6,
        "inflation_mitigation_percent": 0.7,
        "inflation_after_mitigation_percent": 1.9
      },
      {
        "market": "New Zealand",
        "media": "Other",
        "total_net_net_spend": 0,
        "total_addressable_net_net_spend": 0,
        "total_net_net_measured": 0,
        "measured_spend_percent": 0.0,
        "savings_value": 0,
        "savings_percent": 0.0,
        "inflation_percent": 0.0,
        "inflation_mitigation_percent": 0.0,
        "inflation_after_mitigation_percent": 0.0
      },
      {
        "market": "New Zealand",
        "media": "TOTAL",
        "total_net_net_spend": 296830,
        "total_addressable_net_net_spend": 296830,
        "total_net_net_measured": 0,
        "measured_spend_percent": 0.0,
        "savings_value": 0,
        "savings_percent": 0.0,
        "inflation_percent": 0.0,
        "inflation_mitigation_percent": 0.0,
        "inflation_after_mitigation_percent": 0.0
      },
      {
        "market": "Nigeria",
        "media": "TV",
        "total_net_net_spend": null,
        "total_addressable_net_net_spend": null,
        "total_net_net_measured": null,
        "measured_spend_percent": 0.0,
        "savings_value": null,
        "savings_percent": 0.0,
        "inflation_percent": 0.0,
        "inflation_mitigation_percent": 0.0,
        "inflation_after_mitigation_percent": false
      },
      {
        "market": "Nigeria",
        "media": "PRINT",
        "total_net_net_spend": null,
        "total_addressable_net_net_spend": null,
        "total_net_net_measured": null,
        "measured_spend_percent": 0.0,
        "savings_value": null,
        "savings_percent": 0.0,
        "inflation_percent": 0.0,
        "inflation_mitigation_percent": 0.0,
        "inflation_after_mitigation_percent": 0.0
      },
      {
        "market": "Nigeria",
        "media": "OUTDOOR",
        "total_net_net_spend": null,
        "total_addressable_net_net_spend": null,
        "total_net_net_measured": null,
        "measured_spend_percent": 0.0,
        "savings_value": null,
        "savings_percent": 0.0,
        "inflation_percent": 0.0,
        "inflation_mitigation_percent": 0.0,
        "inflation_after_mitigation_percent": false
      },
      {
        "market": "Nigeria",
        "media": "ONLINE",
        "total_net_net_spend": null,
        "total_addressable_net_net_spend": null,
        "total_net_net_measured": null,
        "measured_spend_percent": 0.0,
        "savings_value": null,
        "savings_percent": 0.0,
        "inflation_percent": 0.0,
        "inflation_mitigation_percent": 0.0,
        "inflation_after_mitigation_percent": false
      },
      {
        "market": "Nigeria",
        "media": "RADIO",
        "total_net_net_spend": null,
        "total_addressable_net_net_spend": null,
        "total_net_net_measured": null,
        "measured_spend_percent": 0.0,
        "savings_value": null,
        "savings_percent": 0.0,
        "inflation_percent": 0.0,
        "inflation_mitigation_percent": 0.0,
        "inflation_after_mitigation_percent": false
      },
      {
        "market": "Nigeria",
        "media": "CINEMA",
        "total_net_net_spend": null,
        "total_addressable_net_net_spend": null,
        "total_net_net_measured": null,
        "measured_spend_percent": 0.0,
        "savings_value": null,
        "savings_percent": 0.0,
        "inflation_percent": 0.0,
        "inflation_mitigation_percent": 0.0,
        "inflation_after_mitigation_percent": false
      },
      {
        "market": "Nigeria",
        "media": "OTHER",
        "total_net_net_spend": null,
        "total_addressable_net_net_spend": null,
        "total_net_net_measured": null,
        "measured_spend_percent": 0.0,
        "savings_value": null,
        "savings_percent": 0.0,
        "inflation_percent": 0.0,
        "inflation_mitigation_percent": 0.0,
        "inflation_after_mitigation_percent": 0.0
      },
      {
        "market": "Nigeria",
        "media": "TOTAL",
        "total_net_net_spend": 0,
        "total_addressable_net_net_spend": 0,
        "total_net_net_measured": 0,
        "measured_spend_percent": 0.0,
        "savings_value": 0,
        "savings_percent": 0.0,
        "inflation_percent": 0.0,
        "inflation_mitigation_percent": 0.0,
        "inflation_after_mitigation_percent": 0.0
      },
      {
        "market": "Poland",
        "media": "TV",
        "total_net_net_spend": 373257,
        "total_addressable_net_net_spend": 373257,
        "total_net_net_measured": 373257,
        "measured_spend_percent": 100.0,
        "savings_value": 168308,
        "savings_percent": 31.08,
        "inflation_percent": 14.8,
        "inflation_mitigation_percent": 14.8,
        "inflation_after_mitigation_percent": 0.0
      },
      {
        "market": "Poland",
        "media": "Print",
        "total_net_net_spend": 0,
        "total_addressable_net_net_spend": 0,
        "total_net_net_measured": 0,
        "measured_spend_percent": 0.0,
        "savings_value": 0,
        "savings_percent": 0.0,
        "inflation_percent": 0.0,
        "inflation_mitigation_percent": 1.4,
        "inflation_after_mitigation_percent": 0.0
      },
      {
        "market": "Poland",
        "media": "OOH",
        "total_net_net_spend": 4295267,
        "total_addressable_net_net_spend": 4295267,
        "total_net_net_measured": 0,
        "measured_spend_percent": 0.0,
        "savings_value": 0,
        "savings_percent": 0.0,
        "inflation_percent": null,
        "inflation_mitigation_percent": null,
        "inflation_after_mitigation_percent": null
      },
      {
        "market": "Poland",
        "media": "Online",
        "total_net_net_spend": 1382155,
        "total_addressable_net_net_spend": 1382155,
        "total_net_net_measured": 0,
        "measured_spend_percent": 0.0,
        "savings_value": 0,
        "savings_percent": 0.0,
        "inflation_percent": 11.0,
        "inflation_mitigation_percent": 11.0,
        "inflation_after_mitigation_percent": 0.0
      },
      {
        "market": "Poland",
        "media": "Radio",
        "total_net_net_spend": 0,
        "total_addressable_net_net_spend": 0,
        "total_net_net_measured": 0,
        "measured_spend_percent": 0.0,
        "savings_value": 0,
        "savings_percent": 0.0,
        "inflation_percent": 7.5,
        "inflation_mitigation_percent": 7.5,
        "inflation_after_mitigation_percent": 0.0
      },
      {
        "market": "Poland",
        "media": "Cinema",
        "total_net_net_spend": 0,
        "total_addressable_net_net_spend": 0,
        "total_net_net_measured": 0,
        "measured_spend_percent": 0.0,
        "savings_value": 0,
        "savings_percent": 0.0,
        "inflation_percent": 4.6,
        "inflation_mitigation_percent": 4.6,
        "inflation_after_mitigation_percent": 0.0
      },
      {
        "market": "Poland",
        "media": "Other",
        "total_net_net_spend": 0,
        "total_addressable_net_net_spend": 0,
        "total_net_net_measured": 0,
        "measured_spend_percent": 0.0,
        "savings_value": 0,
        "savings_percent": 0.0,
        "inflation_percent": 0.0,
        "inflation_mitigation_percent": 0.0,
        "inflation_after_mitigation_percent": 0.0
      },
      {
        "market": "Poland",
        "media": "TOTAL",
        "total_net_net_spend": 6050679,
        "total_addressable_net_net_spend": 6050679,
        "total_net_net_measured": 373257,
        "measured_spend_percent": 6.2,
        "savings_value": 168308,
        "savings_percent": 31.1,
        "inflation_percent": 0.0,
        "inflation_mitigation_percent": 0.0,
        "inflation_after_mitigation_percent": 0.0
      },
      {
        "market": "Spain",
        "media": "TV",
        "total_net_net_spend": 213830,
        "total_addressable_net_net_spend": 213830,
        "total_net_net_measured": 213830,
        "measured_spend_percent": 100.0,
        "savings_value": -10902,
        "savings_percent": -5.37,
        "inflation_percent": 7.6,
        "inflation_mitigation_percent": 7.6,
        "inflation_after_mitigation_percent": 0.0
      },
      {
        "market": "Spain",
        "media": "Print",
        "total_net_net_spend": 5500,
        "total_addressable_net_net_spend": 5500,
        "total_net_net_measured": 0,
        "measured_spend_percent": 0.0,
        "savings_value": 0,
        "savings_percent": 0.0,
        "inflation_percent": 0.0,
        "inflation_mitigation_percent": 0.6,
        "inflation_after_mitigation_percent": 0.0
      },
      {
        "market": "Spain",
        "media": "OOH",
        "total_net_net_spend": 109482,
        "total_addressable_net_net_spend": 109482,
        "total_net_net_measured": 0,
        "measured_spend_percent": 0.0,
        "savings_value": 0,
        "savings_percent": 0.0,
        "inflation_percent": null,
        "inflation_mitigation_percent": null,
        "inflation_after_mitigation_percent": null
      },
      {
        "market": "Spain",
        "media": "Online",
        "total_net_net_spend": 306066,
        "total_addressable_net_net_spend": 306066,
        "total_net_net_measured": 194566,
        "measured_spend_percent": 63.6,
        "savings_value": 1172,
        "savings_percent": 0.6,
        "inflation_percent": 5.0,
        "inflation_mitigation_percent": 5.0,
        "inflation_after_mitigation_percent": 0.0
      },
      {
        "market": "Spain",
        "media": "Radio",
        "total_net_net_spend": 0,
        "total_addressable_net_net_spend": 0,
        "total_net_net_measured": 0,
        "measured_spend_percent": 0.0,
        "savings_value": 0,
        "savings_percent": 0.0,
        "inflation_percent": 3.3,
        "inflation_mitigation_percent": 3.3,
        "inflation_after_mitigation_percent": 0.0
      },
      {
        "market": "Spain",
        "media": "Cinema",
        "total_net_net_spend": 0,
        "total_addressable_net_net_spend": 0,
        "total_net_net_measured": 0,
        "measured_spend_percent": 0.0,
        "savings_value": 0,
        "savings_percent": 0.0,
        "inflation_percent": 2.1,
        "inflation_mitigation_percent": 2.1,
        "inflation_after_mitigation_percent": 0.0
      },
      {
        "market": "Spain",
        "media": "Other",
        "total_net_net_spend": 0,
        "total_addressable_net_net_spend": 0,
        "total_net_net_measured": 0,
        "measured_spend_percent": 0.0,
        "savings_value": 0,
        "savings_percent": 0.0,
        "inflation_percent": 0.0,
        "inflation_mitigation_percent": 0.0,
        "inflation_after_mitigation_percent": 0.0
      },
      {
        "market": "Spain",
        "media": "TOTAL",
        "total_net_net_spend": 634877,
        "total_addressable_net_net_spend": 634877,
        "total_net_net_measured": 408396,
        "measured_spend_percent": 64.3,
        "savings_value": -9730,
        "savings_percent": -2.4,
        "inflation_percent": 0.0,
        "inflation_mitigation_percent": 0.0,
        "inflation_after_mitigation_percent": 0.0
      },
      {
        "market": "Sweden",
        "media": "TV",
        "total_net_net_spend": 0,
        "total_addressable_net_net_spend": 0,
        "total_net_net_measured": 0,
        "measured_spend_percent": 100.0,
        "savings_value": -4415327,
        "savings_percent": 100.0,
        "inflation_percent": 7.4,
        "inflation_mitigation_percent": 1.2,
        "inflation_after_mitigation_percent": 3.5
      },
      {
        "market": "Sweden",
        "media": "Print",
        "total_net_net_spend": 260841,
        "total_addressable_net_net_spend": 260841,
        "total_net_net_measured": 0,
        "measured_spend_percent": 0.0,
        "savings_value": 0,
        "savings_percent": 0.0,
        "inflation_percent": 0.0,
        "inflation_mitigation_percent": 0.4,
        "inflation_after_mitigation_percent": 0.7
      },
      {
        "market": "Sweden",
        "media": "OOH",
        "total_net_net_spend": 13677846,
        "total_addressable_net_net_spend": 13677846,
        "total_net_net_measured": 0,
        "measured_spend_percent": 0.0,
        "savings_value": 0,
        "savings_percent": 0.0,
        "inflation_percent": null,
        "inflation_mitigation_percent": 1.9,
        "inflation_after_mitigation_percent": 6.3
      },
      {
        "market": "Sweden",
        "media": "Online",
        "total_net_net_spend": 0,
        "total_addressable_net_net_spend": 0,
        "total_net_net_measured": 0,
        "measured_spend_percent": 94.3,
        "savings_value": -58866,
        "savings_percent": 100.0,
        "inflation_percent": 4.0,
        "inflation_mitigation_percent": 0.1,
        "inflation_after_mitigation_percent": 0.4
      },
      {
        "market": "Sweden",
        "media": "Radio",
        "total_net_net_spend": 386702,
        "total_addressable_net_net_spend": 386702,
        "total_net_net_measured": 386702,
        "measured_spend_percent": 94.4,
        "savings_value": 52195,
        "savings_percent": 11.9,
        "inflation_percent": 12.0,
        "inflation_mitigation_percent": 1.5,
        "inflation_after_mitigation_percent": 3.7
      },
      {
        "market": "Sweden",
        "media": "Cinema",
        "total_net_net_spend": 0,
        "total_addressable_net_net_spend": 0,
        "total_net_net_measured": 0,
        "measured_spend_percent": 100.0,
        "savings_value": 0,
        "savings_percent": 0.0,
        "inflation_percent": 3.0,
        "inflation_mitigation_percent": 1.7,
        "inflation_after_mitigation_percent": 4.3
      },
      {
        "market": "Sweden",
        "media": "Other",
        "total_net_net_spend": 0,
        "total_addressable_net_net_spend": 0,
        "total_net_net_measured": 0,
        "measured_spend_percent": 0.0,
        "savings_value": 0,
        "savings_percent": 0.0,
        "inflation_percent": 0.0,
        "inflation_mitigation_percent": 0.0,
        "inflation_after_mitigation_percent": 0.0
      },
      {
        "market": "Sweden",
        "media": "TOTAL",
        "total_net_net_spend": 14325389,
        "total_addressable_net_net_spend": 14325389,
        "total_net_net_measured": 386702,
        "measured_spend_percent": 2.7,
        "savings_value": -4421998,
        "savings_percent": 109.6,
        "inflation_percent": 0.0,
        "inflation_mitigation_percent": 0.0,
        "inflation_after_mitigation_percent": 0.0
      },
      {
        "market": "UK",
        "media": "TV",
        "total_net_net_spend": 2617284,
        "total_addressable_net_net_spend": 2617284,
        "total_net_net_measured": 2601702,
        "measured_spend_percent": 99.4,
        "savings_value": -282857,
        "savings_percent": -12.2,
        "inflation_percent": 0.0,
        "inflation_mitigation_percent": 0.0,
        "inflation_after_mitigation_percent": 0.0
      },
      {
        "market": "UK",
        "media": "Print",
        "total_net_net_spend": 0,
        "total_addressable_net_net_spend": 0,
        "total_net_net_measured": 0,
        "measured_spend_percent": 0.0,
        "savings_value": 0,
        "savings_percent": 0.0,
        "inflation_percent": 0.0,
        "inflation_mitigation_percent": 0.0,
        "inflation_after_mitigation_percent": 0.0
      },
      {
        "market": "UK",
        "media": "OOH",
        "total_net_net_spend": 5344838,
        "total_addressable_net_net_spend": 5344838,
        "total_net_net_measured": 5344838,
        "measured_spend_percent": 100.0,
        "savings_value": 0,
        "savings_percent": 0.0,
        "inflation_percent": null,
        "inflation_mitigation_percent": null,
        "inflation_after_mitigation_percent": null
      },
      {
        "market": "UK",
        "media": "Online",
        "total_net_net_spend": 2401724,
        "total_addressable_net_net_spend": 2401724,
        "total_net_net_measured": 1377610,
        "measured_spend_percent": 57.4,
        "savings_value": 29997,
        "savings_percent": 2.1,
        "inflation_percent": 0.0,
        "inflation_mitigation_percent": 0.0,
        "inflation_after_mitigation_percent": false
      },
      {
        "market": "UK",
        "media": "Radio",
        "total_net_net_spend": 0,
        "total_addressable_net_net_spend": 0,
        "total_net_net_measured": 0,
        "measured_spend_percent": 0.0,
        "savings_value": 0,
        "savings_percent": 0.0,
        "inflation_percent": 0.0,
        "inflation_mitigation_percent": 0.0,
        "inflation_after_mitigation_percent": false
      },
      {
        "market": "UK",
        "media": "Cinema",
        "total_net_net_spend": 0,
        "total_addressable_net_net_spend": 0,
        "total_net_net_measured": 0,
        "measured_spend_percent": 0.0,
        "savings_value": 0,
        "savings_percent": 0.0,
        "inflation_percent": 0.0,
        "inflation_mitigation_percent": 0.0,
        "inflation_after_mitigation_percent": false
      },
      {
        "market": "UK",
        "media": "Other",
        "total_net_net_spend": 0,
        "total_addressable_net_net_spend": 0,
        "total_net_net_measured": 0,
        "measured_spend_percent": 0.0,
        "savings_value": 0,
        "savings_percent": 0.0,
        "inflation_percent": 0.0,
        "inflation_mitigation_percent": 0.0,
        "inflation_after_mitigation_percent": 0.0
      },
      {
        "market": "UK",
        "media": "TOTAL",
        "total_net_net_spend": 10363846,
        "total_addressable_net_net_spend": 10363846,
        "total_net_net_measured": 9324150,
        "measured_spend_percent": 90.0,
        "savings_value": -252861,
        "savings_percent": -2.8,
        "inflation_percent": 0.0,
        "inflation_mitigation_percent": 0.0,
        "inflation_after_mitigation_percent": 0.0
      },
      {
        "market": "",
        "media": "TV",
        "total_net_net_spend": null,
        "total_addressable_net_net_spend": null,
        "total_net_net_measured": null,
        "measured_spend_percent": 0.0,
        "savings_value": null,
        "savings_percent": 0.0,
        "inflation_percent": 0.0,
        "inflation_mitigation_percent": 0.0,
        "inflation_after_mitigation_percent": 0.0
      },
      {
        "market": "",
        "media": "PRINT",
        "total_net_net_spend": null,
        "total_addressable_net_net_spend": null,
        "total_net_net_measured": null,
        "measured_spend_percent": 0.0,
        "savings_value": null,
        "savings_percent": 0.0,
        "inflation_percent": 0.0,
        "inflation_mitigation_percent": 0.0,
        "inflation_after_mitigation_percent": 0.0
      },
      {
        "market": "",
        "media": "OUTDOOR",
        "total_net_net_spend": null,
        "total_addressable_net_net_spend": null,
        "total_net_net_measured": null,
        "measured_spend_percent": 0.0,
        "savings_value": null,
        "savings_percent": 0.0,
        "inflation_percent": 0.0,
        "inflation_mitigation_percent": 0.0,
        "inflation_after_mitigation_percent": 0.0
      },
      {
        "market": "",
        "media": "ONLINE",
        "total_net_net_spend": null,
        "total_addressable_net_net_spend": null,
        "total_net_net_measured": null,
        "measured_spend_percent": 0.0,
        "savings_value": null,
        "savings_percent": 0.0,
        "inflation_percent": 0.0,
        "inflation_mitigation_percent": 0.0,
        "inflation_after_mitigation_percent": 0.0
      },
      {
        "market": "",
        "media": "RADIO",
        "total_net_net_spend": null,
        "total_addressable_net_net_spend": null,
        "total_net_net_measured": null,
        "measured_spend_percent": 0.0,
        "savings_value": null,
        "savings_percent": 0.0,
        "inflation_percent": 0.0,
        "inflation_mitigation_percent": 0.0,
        "inflation_after_mitigation_percent": 0.0
      },
      {
        "market": "",
        "media": "CINEMA",
        "total_net_net_spend": null,
        "total_addressable_net_net_spend": null,
        "total_net_net_measured": null,
        "measured_spend_percent": 0.0,
        "savings_value": null,
        "savings_percent": 0.0,
        "inflation_percent": 0.0,
        "inflation_mitigation_percent": 0.0,
        "inflation_after_mitigation_percent": 0.0
      },
      {
        "market": "",
        "media": "OTHER",
        "total_net_net_spend": null,
        "total_addressable_net_net_spend": null,
        "total_net_net_measured": null,
        "measured_spend_percent": 0.0,
        "savings_value": null,
        "savings_percent": 0.0,
        "inflation_percent": 0.0,
        "inflation_mitigation_percent": 0.0,
        "inflation_after_mitigation_percent": 0.0
      },
      {
        "market": "",
        "media": "TOTAL",
        "total_net_net_spend": 0,
        "total_addressable_net_net_spend": 0,
        "total_net_net_measured": 0,
        "measured_spend_percent": 0.0,
        "savings_value": 0,
        "savings_percent": 0.0,
        "inflation_percent": 0.0,
        "inflation_mitigation_percent": 0.0,
        "inflation_after_mitigation_percent": 0.0
      }
    ]
  }
}